awswafip/__init__.py
awswafip/aws_actions.py
awswafip/file_actions.py
awswafip/updateips.py
awswafip-0.1.3.3.dist-info/METADATA
awswafip-0.1.3.3.dist-info/RECORD
awswafip-0.1.3.3.dist-info/WHEEL
awswafip-0.1.3.3.dist-info/entry_points.txt
awswafip-0.1.3.3.dist-info/top_level.txt
