Metadata-Version: 2.1
Name: awswafip
Version: 0.1.3.3
Summary: Insert/Delete IP Address from a file in IP Address Conditions in AWS WAF
Home-page: https://github.com/parolin/awswafip
Author: Matheus L Parolin
Author-email: mlparolin@gmail.com
License: GNU v3.0
Platform: UNKNOWN
Requires-Dist: boto3
